trinity_connect_client/__init__.py
trinity_connect_client/decorators.py
trinity_connect_client/exceptions/__init__.py
trinity_connect_client/main.py
trinity_connect_client/mixins/__init__.py
trinity_connect_client/models/__init__.py
trinity_connect_client/models/base.py
trinity_connect_client/models/device.py
trinity_connect_client/models/org.py
trinity_connect_client/modules/__init__.py
trinity_connect_client/modules/devices/__init__.py
trinity_connect_client/modules/orgs/__init__.py
trinity_connect_client/py.typed
trinity_connect_client/validators.py
trinity_connect_client-0.2.0.dist-info/WHEEL
trinity_connect_client-0.2.0.dist-info/METADATA
trinity_connect_client-0.2.0.dist-info/RECORD
