Metadata-Version: 2.3
Name: trinity-connect-client
Version: 0.2.0
Summary: Official Python library for Trinity IoT Connect API interactions
Author: Jan Badenhorst, Andries Niemandt
Author-email: Jan Badenhorst <jan.badenhorst@trintel.co.za>, Andries Niemandt <andries.niemandt@trintel.co.za>
Classifier: Programming Language :: Python :: 3
Classifier: License :: OSI Approved :: MIT License
Classifier: Operating System :: OS Independent
Requires-Dist: requests>=2.32.4
Requires-Python: >=3.12
Project-URL: Homepage, https://github.com/trinity-telecomms/connect-py-client
Project-URL: Issues, https://github.com/trinity-telecomms/connect-py-client/issues
